MANIFEST.in
__info__.py
setup.py
wsgi.py
./appomaticcore.egg-info/SOURCES.txt
./appomaticcore.egg-info/dependency_links.txt
./appomaticcore.egg-info/entry_points.txt
./appomaticcore.egg-info/requires.txt
./appomaticcore.egg-info/top_level.txt
appomatic/__init__.py
appomatic/manage.py
appomatic/settings.py
appomatic/urls.py
appomatic/utils/__init__.py
appomatic/utils/app.py
appomatic/utils/forrest.py
appomatic/utils/pwd_stub.py
appomatic/utils/rad_util.py
appomatic/utils/sysconfig_stub.py
appomatic/utils/topsort.py
appomaticcore.egg-info/PKG-INFO
appomaticcore.egg-info/SOURCES.txt
appomaticcore.egg-info/dependency_links.txt
appomaticcore.egg-info/entry_points.txt
appomaticcore.egg-info/requires.txt
appomaticcore.egg-info/top_level.txt