Metadata-Version: 1.0
Name: appomaticcore
Version: 0.0.31
Summary: Appomatic is a userfriendly Django environment with automatic plugin (app) management based on pip.
Home-page: http://github.com/redhog/appomatic
Author: RedHog (Egil Moeller)
Author-email: egil.moller@freecode.no
License: GPL
Keywords: appomatic django apps pip
Platform: UNKNOWN
